auto_tabnet/__init__.py
auto_tabnet/auto_tabnet.py
auto_tabnet-0.0.1.dist-info/LICENSE
auto_tabnet-0.0.1.dist-info/METADATA
auto_tabnet-0.0.1.dist-info/WHEEL
auto_tabnet-0.0.1.dist-info/top_level.txt
auto_tabnet-0.0.1.dist-info/RECORD
