Metadata-Version: 2.1
Name: auto-tabnet
Version: 0.0.1
Summary: Automated implementation of Google TabNet.
Home-page: https://github.com/ersilia-os/auto-tabnet
Download-URL: https://github.com/ersilia-os/auto-tabnet/archive/refs/tags/v1.0.0.tar.gz
Author: Ersilia
Author-email: hello@ersilia.io
Keywords: automl,tabular
License-File: LICENSE
